plausible_events/__init__.py
plausible_events/version.py
plausible_events-0.1.0.dist-info/LICENSE
plausible_events-0.1.0.dist-info/METADATA
plausible_events-0.1.0.dist-info/WHEEL
plausible_events-0.1.0.dist-info/top_level.txt
plausible_events-0.1.0.dist-info/RECORD
