Metadata-Version: 2.1
Name: plausible-events
Version: 0.1.0
Summary: Plausible.io Events API
Home-page: https://github.com/uschmidt83/plausible-events
Author: Uwe Schmidt
Author-email: mail@uweschmidt.org
License: BSD 3-Clause License
Platform: UNKNOWN
Classifier: Development Status :: 4 - Beta
Classifier: Intended Audience :: Science/Research
Classifier: Intended Audience :: Developers
Classifier: License :: OSI Approved :: BSD License
Classifier: Operating System :: OS Independent
Classifier: Programming Language :: Python :: 3 :: Only
Requires-Python: >=3.7
Requires-Dist: requests
